atc_thrift/Atcd.py
atc_thrift/__init__.py
atc_thrift/constants.py
atc_thrift/ttypes.py
atc_thrift-0.1.6.dist-info/DESCRIPTION.rst
atc_thrift-0.1.6.dist-info/METADATA
atc_thrift-0.1.6.dist-info/RECORD
atc_thrift-0.1.6.dist-info/WHEEL
atc_thrift-0.1.6.dist-info/metadata.json
atc_thrift-0.1.6.dist-info/top_level.txt
