Metadata-Version: 2.0
Name: atc-thrift
Version: 0.1.6
Summary: ATC Thrift Library
Home-page: https://github.com/facebook/augmented-traffic-control
Author: Emmanuel Bretelle
Author-email: chantra@fb.com
License: UNKNOWN
Platform: UNKNOWN
Classifier: Programming Language :: Python
Requires-Dist: thrift
